{
"slug": "magnesium-glycinate-vs-citrate",
"title": "Magnesium glycinate vs citrate: what’s the difference?",
"date": "2025-08-23",
"excerpt": "Both provide magnesium; glycinate is often gentler, citrate can be more laxative.",
"contentHtml": "<p>Glycinate is often chosen for its gentler GI profile and evening use. Citrate is widely available and may be more laxative at higher doses. In both cases, check total elemental magnesium and split doses for tolerance.</p><ul><li><strong>Glycinate:</strong> commonly evening or with meals</li><li><strong>Citrate:</strong> with meals; consider evening if laxative effects occur</li></ul>"
}
